cyberwave/__init__.py
cyberwave/assets.pyi
cyberwave/assets_capabilities.json
cyberwave/camera.py
cyberwave/client.py
cyberwave/client.pyi
cyberwave/compact.py
cyberwave/config.py
cyberwave/constants.py
cyberwave/controller.py
cyberwave/exceptions.py
cyberwave/keyboard.py
cyberwave/motion.py
cyberwave/mqtt/README.md
cyberwave/mqtt/__init__.py
cyberwave/mqtt_client.py
cyberwave/navigation.py
cyberwave/py.typed
cyberwave/resources.py
cyberwave/rest/README.md
cyberwave/rest/__init__.py
cyberwave/rest/api/__init__.py
cyberwave/rest/api/catalog_api.py
cyberwave/rest/api/contact_api.py
cyberwave/rest/api/crm_api.py
cyberwave/rest/api/crm_inbox_api.py
cyberwave/rest/api/default_api.py
cyberwave/rest/api/features_api.py
cyberwave/rest/api/profile_api.py
cyberwave/rest/api_client.py
cyberwave/rest/api_response.py
cyberwave/rest/configuration.py
cyberwave/rest/exceptions.py
cyberwave/rest/models/__init__.py
cyberwave/rest/models/add_member_by_email_request.py
cyberwave/rest/models/add_member_by_email_response.py
cyberwave/rest/models/add_member_user_schema.py
cyberwave/rest/models/asset_catalog_import_schema.py
cyberwave/rest/models/asset_create_schema.py
cyberwave/rest/models/asset_create_with_urdf_schema.py
cyberwave/rest/models/asset_glb_from_attachment_schema.py
cyberwave/rest/models/asset_list_schema.py
cyberwave/rest/models/asset_schema.py
cyberwave/rest/models/asset_update_schema.py
cyberwave/rest/models/attachment_create_schema.py
cyberwave/rest/models/attachment_schema.py
cyberwave/rest/models/available_features_schema.py
cyberwave/rest/models/bulk_joint_states_update_schema.py
cyberwave/rest/models/business_event_create_schema.py
cyberwave/rest/models/business_event_list_response_schema.py
cyberwave/rest/models/business_event_schema.py
cyberwave/rest/models/catalog_seed_group_schema.py
cyberwave/rest/models/catalog_seed_item_schema.py
cyberwave/rest/models/catalog_seed_option_schema.py
cyberwave/rest/models/catalog_seed_options_response_schema.py
cyberwave-0.3.3.dist-info/METADATA
cyberwave-0.3.3.dist-info/WHEEL
cyberwave-0.3.3.dist-info/entry_points.txt
cyberwave-0.3.3.dist-info/licenses/LICENSE
cyberwave-0.3.3.dist-info/RECORD
