Metadata-Version: 2.4
Name: cyberwave
Version: 0.3.3
Summary: Python SDK for Cyberwave
License-File: LICENSE
Author: Simone Di Somma
Author-email: sdisomma@cyberwave.com
Requires-Python: >=3.10,<4.0
Classifier: Programming Language :: Python :: 3
Classifier: Programming Language :: Python :: 3.10
Classifier: Programming Language :: Python :: 3.11
Classifier: Programming Language :: Python :: 3.12
Classifier: Programming Language :: Python :: 3.13
Classifier: Programming Language :: Python :: 3.14
Provides-Extra: camera
Provides-Extra: realsense
Requires-Dist: aiortc (>=1.5.0,<2.0.0) ; extra == "camera" or extra == "realsense"
Requires-Dist: av (>=16.0.1,<17.0.0) ; extra == "camera" or extra == "realsense"
Requires-Dist: opencv-python (>=4.8.0,<5.0.0) ; extra == "camera" or extra == "realsense"
Requires-Dist: paho-mqtt (>=2.1.0,<3.0.0)
Requires-Dist: pydantic (>=2,<3)
Requires-Dist: python-dateutil (>=2.8.2,<3.0.0)
Requires-Dist: typing-extensions (>=4.7.1,<5.0.0)
Requires-Dist: urllib3 (>=2.1.0,<3.0.0)
